ManimExtras/__init__.py
ManimExtras/animations.py
ManimExtras/mobjects.py
ManimExtras/utils.py
manim_extras-0.1.dist-info/LICENSE
manim_extras-0.1.dist-info/METADATA
manim_extras-0.1.dist-info/WHEEL
manim_extras-0.1.dist-info/top_level.txt
manim_extras-0.1.dist-info/RECORD
