Metadata-Version: 2.1
Name: manim-extras
Version: 0.1
Summary: Addons to Manim Community
Home-page: https://github.com/wafarm/ManimExtras
Author: Wafarm
Author-email: qinyy07@gmail.com
Project-URL: Bug Tracker, https://github.com/wafarm/ManimExtras/issues
Classifier: Programming Language :: Python :: 3
Classifier: License :: OSI Approved :: MIT License
Classifier: Operating System :: OS Independent
Requires-Python: >=3.6
License-File: LICENSE
Requires-Dist: numpy
Requires-Dist: manim
